nanogram/__init__.py
nanogram/_backend.cpython-311-darwin.so
nanogram-0.0.1.dev0.dist-info/METADATA
nanogram-0.0.1.dev0.dist-info/WHEEL
nanogram-0.0.1.dev0.dist-info/entry_points.txt
nanogram-0.0.1.dev0.dist-info/RECORD
