Metadata-Version: 2.1
Name: nanogram
Version: 0.0.1.dev0
Summary: Lightweight and fast histogramming in Python
Author-Email: Doug Davis <ddavis@ddavis.io>
Maintainer-Email: Doug Davis <ddavis@ddavis.io>
Classifier: Programming Language :: Python :: 3 :: Only
Classifier: Programming Language :: Python :: 3.8
Classifier: Programming Language :: Python :: 3.9
Classifier: Programming Language :: Python :: 3.10
Classifier: Programming Language :: Python :: 3.11
Classifier: Programming Language :: C++
Classifier: Operating System :: Unix
Classifier: Operating System :: MacOS
Classifier: Operating System :: POSIX
Classifier: Operating System :: POSIX :: Linux
Classifier: Operating System :: Microsoft :: Windows
Classifier: License :: OSI Approved :: MIT License
Classifier: Intended Audience :: Science/Research
Classifier: Development Status :: 6 - Mature
Requires-Python: >=3.8
Requires-Dist: numpy
